{
  "_format": "hh-sol-cache-2",
  "files": {
    "/Volumes/N/CoopHive/hive/hardhat/contracts/ControllerOwnable.sol": {
      "lastModificationDate": 1706383118872,
      "contentHash": "e3e94a6c141b87209b278446d1ae8bb8",
      "sourceName": "contracts/ControllerOwnable.sol",
      "solcConfig": {
        "version": "0.8.21",
        "settings": {
          "evmVersion": "paris",
          "optimizer": {
            "enabled": false,
            "runs": 200
          },
          "outputSelection": {
            "*": {
              "*": [
                "abi",
                "evm.bytecode",
                "evm.deployedBytecode",
                "evm.methodIdentifiers",
                "metadata",
                "devdoc",
                "userdoc",
                "storageLayout",
                "evm.gasEstimates"
              ],
              "": [
                "ast"
              ]
            }
          },
          "metadata": {
            "useLiteralContent": true
          }
        }
      },
      "imports": [
        "@openzeppelin/contracts/access/Ownable.sol"
      ],
      "versionPragmas": [
        "^0.8.6"
      ],
      "artifacts": [
        "ControllerOwnable"
      ]
    },
    "/Volumes/N/CoopHive/hive/hardhat/node_modules/.pnpm/@openzeppelin+contracts@4.9.5/node_modules/@openzeppelin/contracts/access/Ownable.sol": {
      "lastModificationDate": 1706734039507,
      "contentHash": "5a20b2cad87ddb61c7a3a6af21289e28",
      "sourceName": "@openzeppelin/contracts/access/Ownable.sol",
      "solcConfig": {
        "version": "0.8.21",
        "settings": {
          "evmVersion": "paris",
          "optimizer": {
            "enabled": false,
            "runs": 200
          },
          "outputSelection": {
            "*": {
              "*": [
                "abi",
                "evm.bytecode",
                "evm.deployedBytecode",
                "evm.methodIdentifiers",
                "metadata",
                "devdoc",
                "userdoc",
                "storageLayout",
                "evm.gasEstimates"
              ],
              "": [
                "ast"
              ]
            }
          },
          "metadata": {
            "useLiteralContent": true
          }
        }
      },
      "imports": [
        "../utils/Context.sol"
      ],
      "versionPragmas": [
        "^0.8.0"
      ],
      "artifacts": [
        "Ownable"
      ]
    },
    "/Volumes/N/CoopHive/hive/hardhat/node_modules/.pnpm/@openzeppelin+contracts@4.9.5/node_modules/@openzeppelin/contracts/utils/Context.sol": {
      "lastModificationDate": 1706734039469,
      "contentHash": "f07feb4a44b1a4872370da5aa70e8e46",
      "sourceName": "@openzeppelin/contracts/utils/Context.sol",
      "solcConfig": {
        "version": "0.8.21",
        "settings": {
          "evmVersion": "paris",
          "optimizer": {
            "enabled": false,
            "runs": 200
          },
          "outputSelection": {
            "*": {
              "*": [
                "abi",
                "evm.bytecode",
                "evm.deployedBytecode",
                "evm.methodIdentifiers",
                "metadata",
                "devdoc",
                "userdoc",
                "storageLayout",
                "evm.gasEstimates"
              ],
              "": [
                "ast"
              ]
            }
          },
          "metadata": {
            "useLiteralContent": true
          }
        }
      },
      "imports": [],
      "versionPragmas": [
        "^0.8.0"
      ],
      "artifacts": [
        "Context"
      ]
    },
    "/Volumes/N/CoopHive/hive/hardhat/contracts/HiveUsers.sol": {
      "lastModificationDate": 1706568289167,
      "contentHash": "2ea691f73fb707cce5ef3a01e81f812c",
      "sourceName": "contracts/HiveUsers.sol",
      "solcConfig": {
        "version": "0.8.21",
        "settings": {
          "evmVersion": "paris",
          "optimizer": {
            "enabled": false,
            "runs": 200
          },
          "outputSelection": {
            "*": {
              "*": [
                "abi",
                "evm.bytecode",
                "evm.deployedBytecode",
                "evm.methodIdentifiers",
                "metadata",
                "devdoc",
                "userdoc",
                "storageLayout",
                "evm.gasEstimates"
              ],
              "": [
                "ast"
              ]
            }
          },
          "metadata": {
            "useLiteralContent": true
          }
        }
      },
      "imports": [
        "@openzeppelin/contracts-upgradeable/proxy/utils/Initializable.sol",
        "./SharedStructs.sol",
        "./ControllerOwnable.sol"
      ],
      "versionPragmas": [
        "^0.8.6"
      ],
      "artifacts": [
        "HiveUsers"
      ]
    },
    "/Volumes/N/CoopHive/hive/hardhat/contracts/SharedStructs.sol": {
      "lastModificationDate": 1707051865134,
      "contentHash": "1c7fc29635552e67f267d3c8eb31a353",
      "sourceName": "contracts/SharedStructs.sol",
      "solcConfig": {
        "version": "0.8.21",
        "settings": {
          "evmVersion": "paris",
          "optimizer": {
            "enabled": false,
            "runs": 200
          },
          "outputSelection": {
            "*": {
              "*": [
                "abi",
                "evm.bytecode",
                "evm.deployedBytecode",
                "evm.methodIdentifiers",
                "metadata",
                "devdoc",
                "userdoc",
                "storageLayout",
                "evm.gasEstimates"
              ],
              "": [
                "ast"
              ]
            }
          },
          "metadata": {
            "useLiteralContent": true
          }
        }
      },
      "imports": [],
      "versionPragmas": [
        "^0.8.6"
      ],
      "artifacts": [
        "SharedStructs"
      ]
    },
    "/Volumes/N/CoopHive/hive/hardhat/node_modules/.pnpm/@openzeppelin+contracts-upgradeable@4.9.5/node_modules/@openzeppelin/contracts-upgradeable/proxy/utils/Initializable.sol": {
      "lastModificationDate": 1706734039621,
      "contentHash": "b0970a564d121abf9adfff8d1a01eb16",
      "sourceName": "@openzeppelin/contracts-upgradeable/proxy/utils/Initializable.sol",
      "solcConfig": {
        "version": "0.8.21",
        "settings": {
          "evmVersion": "paris",
          "optimizer": {
            "enabled": false,
            "runs": 200
          },
          "outputSelection": {
            "*": {
              "*": [
                "abi",
                "evm.bytecode",
                "evm.deployedBytecode",
                "evm.methodIdentifiers",
                "metadata",
                "devdoc",
                "userdoc",
                "storageLayout",
                "evm.gasEstimates"
              ],
              "": [
                "ast"
              ]
            }
          },
          "metadata": {
            "useLiteralContent": true
          }
        }
      },
      "imports": [
        "../../utils/AddressUpgradeable.sol"
      ],
      "versionPragmas": [
        "^0.8.2"
      ],
      "artifacts": [
        "Initializable"
      ]
    },
    "/Volumes/N/CoopHive/hive/hardhat/node_modules/.pnpm/@openzeppelin+contracts-upgradeable@4.9.5/node_modules/@openzeppelin/contracts-upgradeable/utils/AddressUpgradeable.sol": {
      "lastModificationDate": 1706734039583,
      "contentHash": "c30c805386fda8a42ff515da963d3a95",
      "sourceName": "@openzeppelin/contracts-upgradeable/utils/AddressUpgradeable.sol",
      "solcConfig": {
        "version": "0.8.21",
        "settings": {
          "evmVersion": "paris",
          "optimizer": {
            "enabled": false,
            "runs": 200
          },
          "outputSelection": {
            "*": {
              "*": [
                "abi",
                "evm.bytecode",
                "evm.deployedBytecode",
                "evm.methodIdentifiers",
                "metadata",
                "devdoc",
                "userdoc",
                "storageLayout",
                "evm.gasEstimates"
              ],
              "": [
                "ast"
              ]
            }
          },
          "metadata": {
            "useLiteralContent": true
          }
        }
      },
      "imports": [],
      "versionPragmas": [
        "^0.8.1"
      ],
      "artifacts": [
        "AddressUpgradeable"
      ]
    },
    "/Volumes/N/CoopHive/hive/hardhat/contracts/HiveStorage.sol": {
      "lastModificationDate": 1708744247018,
      "contentHash": "14681623a441098a6c1360390dcf58c8",
      "sourceName": "contracts/HiveStorage.sol",
      "solcConfig": {
        "version": "0.8.21",
        "settings": {
          "evmVersion": "paris",
          "optimizer": {
            "enabled": false,
            "runs": 200
          },
          "outputSelection": {
            "*": {
              "*": [
                "abi",
                "evm.bytecode",
                "evm.deployedBytecode",
                "evm.methodIdentifiers",
                "metadata",
                "devdoc",
                "userdoc",
                "storageLayout",
                "evm.gasEstimates"
              ],
              "": [
                "ast"
              ]
            }
          },
          "metadata": {
            "useLiteralContent": true
          }
        }
      },
      "imports": [
        "@openzeppelin/contracts-upgradeable/proxy/utils/Initializable.sol",
        "./SharedStructs.sol",
        "./ControllerOwnable.sol"
      ],
      "versionPragmas": [
        "^0.8.6"
      ],
      "artifacts": [
        "HiveStorage"
      ]
    },
    "/Volumes/N/CoopHive/hive/hardhat/contracts/HiveMediationRandom.sol": {
      "lastModificationDate": 1707051865132,
      "contentHash": "a2027ff9082a8c7f48504608563177c1",
      "sourceName": "contracts/HiveMediationRandom.sol",
      "solcConfig": {
        "version": "0.8.21",
        "settings": {
          "evmVersion": "paris",
          "optimizer": {
            "enabled": false,
            "runs": 200
          },
          "outputSelection": {
            "*": {
              "*": [
                "abi",
                "evm.bytecode",
                "evm.deployedBytecode",
                "evm.methodIdentifiers",
                "metadata",
                "devdoc",
                "userdoc",
                "storageLayout",
                "evm.gasEstimates"
              ],
              "": [
                "ast"
              ]
            }
          },
          "metadata": {
            "useLiteralContent": true
          }
        }
      },
      "imports": [
        "@openzeppelin/contracts-upgradeable/proxy/utils/Initializable.sol",
        "./ControllerOwnable.sol",
        "./SharedStructs.sol",
        "./IHiveMediation.sol"
      ],
      "versionPragmas": [
        "^0.8.6"
      ],
      "artifacts": [
        "HiveMediationRandom"
      ]
    },
    "/Volumes/N/CoopHive/hive/hardhat/contracts/HiveController.sol": {
      "lastModificationDate": 1708743856066,
      "contentHash": "5e892ba4c9b06699383a8e3042356ade",
      "sourceName": "contracts/HiveController.sol",
      "solcConfig": {
        "version": "0.8.21",
        "settings": {
          "evmVersion": "paris",
          "optimizer": {
            "enabled": false,
            "runs": 200
          },
          "outputSelection": {
            "*": {
              "*": [
                "abi",
                "evm.bytecode",
                "evm.deployedBytecode",
                "evm.methodIdentifiers",
                "metadata",
                "devdoc",
                "userdoc",
                "storageLayout",
                "evm.gasEstimates"
              ],
              "": [
                "ast"
              ]
            }
          },
          "metadata": {
            "useLiteralContent": true
          }
        }
      },
      "imports": [
        "@openzeppelin/contracts/access/Ownable.sol",
        "@openzeppelin/contracts-upgradeable/proxy/utils/Initializable.sol",
        "./SharedStructs.sol",
        "./IHiveController.sol",
        "./IHiveStorage.sol",
        "./IHivePayments.sol",
        "./IHiveMediation.sol"
      ],
      "versionPragmas": [
        "^0.8.6"
      ],
      "artifacts": [
        "HiveController"
      ]
    },
    "/Volumes/N/CoopHive/hive/hardhat/contracts/IHiveMediation.sol": {
      "lastModificationDate": 1706568289169,
      "contentHash": "90d9c98405120b5abd59f75e83214e79",
      "sourceName": "contracts/IHiveMediation.sol",
      "solcConfig": {
        "version": "0.8.21",
        "settings": {
          "evmVersion": "paris",
          "optimizer": {
            "enabled": false,
            "runs": 200
          },
          "outputSelection": {
            "*": {
              "*": [
                "abi",
                "evm.bytecode",
                "evm.deployedBytecode",
                "evm.methodIdentifiers",
                "metadata",
                "devdoc",
                "userdoc",
                "storageLayout",
                "evm.gasEstimates"
              ],
              "": [
                "ast"
              ]
            }
          },
          "metadata": {
            "useLiteralContent": true
          }
        }
      },
      "imports": [
        "./SharedStructs.sol"
      ],
      "versionPragmas": [
        "^0.8.6"
      ],
      "artifacts": [
        "IHiveMediationHandler",
        "IHiveMediationRequester"
      ]
    },
    "/Volumes/N/CoopHive/hive/hardhat/contracts/IHiveController.sol": {
      "lastModificationDate": 1706568289167,
      "contentHash": "af1b4d281b9bc08b9e2f292f9be71ee0",
      "sourceName": "contracts/IHiveController.sol",
      "solcConfig": {
        "version": "0.8.21",
        "settings": {
          "evmVersion": "paris",
          "optimizer": {
            "enabled": false,
            "runs": 200
          },
          "outputSelection": {
            "*": {
              "*": [
                "abi",
                "evm.bytecode",
                "evm.deployedBytecode",
                "evm.methodIdentifiers",
                "metadata",
                "devdoc",
                "userdoc",
                "storageLayout",
                "evm.gasEstimates"
              ],
              "": [
                "ast"
              ]
            }
          },
          "metadata": {
            "useLiteralContent": true
          }
        }
      },
      "imports": [
        "./SharedStructs.sol"
      ],
      "versionPragmas": [
        "^0.8.6"
      ],
      "artifacts": [
        "IHiveController"
      ]
    },
    "/Volumes/N/CoopHive/hive/hardhat/contracts/IHiveStorage.sol": {
      "lastModificationDate": 1706568289169,
      "contentHash": "e2a505118b068568828c9d8ef1bc23ac",
      "sourceName": "contracts/IHiveStorage.sol",
      "solcConfig": {
        "version": "0.8.21",
        "settings": {
          "evmVersion": "paris",
          "optimizer": {
            "enabled": false,
            "runs": 200
          },
          "outputSelection": {
            "*": {
              "*": [
                "abi",
                "evm.bytecode",
                "evm.deployedBytecode",
                "evm.methodIdentifiers",
                "metadata",
                "devdoc",
                "userdoc",
                "storageLayout",
                "evm.gasEstimates"
              ],
              "": [
                "ast"
              ]
            }
          },
          "metadata": {
            "useLiteralContent": true
          }
        }
      },
      "imports": [
        "./SharedStructs.sol"
      ],
      "versionPragmas": [
        "^0.8.6"
      ],
      "artifacts": [
        "IHiveStorage"
      ]
    },
    "/Volumes/N/CoopHive/hive/hardhat/contracts/IHivePayments.sol": {
      "lastModificationDate": 1706568289169,
      "contentHash": "e5d002d17659c4a009e8a5104d6a04e7",
      "sourceName": "contracts/IHivePayments.sol",
      "solcConfig": {
        "version": "0.8.21",
        "settings": {
          "evmVersion": "paris",
          "optimizer": {
            "enabled": false,
            "runs": 200
          },
          "outputSelection": {
            "*": {
              "*": [
                "abi",
                "evm.bytecode",
                "evm.deployedBytecode",
                "evm.methodIdentifiers",
                "metadata",
                "devdoc",
                "userdoc",
                "storageLayout",
                "evm.gasEstimates"
              ],
              "": [
                "ast"
              ]
            }
          },
          "metadata": {
            "useLiteralContent": true
          }
        }
      },
      "imports": [],
      "versionPragmas": [
        "^0.8.6"
      ],
      "artifacts": [
        "IHivePayments"
      ]
    },
    "/Volumes/N/CoopHive/hive/hardhat/contracts/HiveStorageTestable.sol": {
      "lastModificationDate": 1706568289167,
      "contentHash": "5b60818a16d2fbba497664051a6d66d8",
      "sourceName": "contracts/HiveStorageTestable.sol",
      "solcConfig": {
        "version": "0.8.21",
        "settings": {
          "evmVersion": "paris",
          "optimizer": {
            "enabled": false,
            "runs": 200
          },
          "outputSelection": {
            "*": {
              "*": [
                "abi",
                "evm.bytecode",
                "evm.deployedBytecode",
                "evm.methodIdentifiers",
                "metadata",
                "devdoc",
                "userdoc",
                "storageLayout",
                "evm.gasEstimates"
              ],
              "": [
                "ast"
              ]
            }
          },
          "metadata": {
            "useLiteralContent": true
          }
        }
      },
      "imports": [
        "./HiveStorage.sol"
      ],
      "versionPragmas": [
        "^0.8.6"
      ],
      "artifacts": [
        "HiveStorageTestable"
      ]
    },
    "/Volumes/N/CoopHive/hive/hardhat/node_modules/.pnpm/@openzeppelin+contracts@4.9.5/node_modules/@openzeppelin/contracts/security/Pausable.sol": {
      "lastModificationDate": 1706734039507,
      "contentHash": "25c8108f36fdd472bc78d4c4af240c11",
      "sourceName": "@openzeppelin/contracts/security/Pausable.sol",
      "solcConfig": {
        "version": "0.8.21",
        "settings": {
          "evmVersion": "paris",
          "optimizer": {
            "enabled": false,
            "runs": 200
          },
          "outputSelection": {
            "*": {
              "*": [
                "abi",
                "evm.bytecode",
                "evm.deployedBytecode",
                "evm.methodIdentifiers",
                "metadata",
                "devdoc",
                "userdoc",
                "storageLayout",
                "evm.gasEstimates"
              ],
              "": [
                "ast"
              ]
            }
          },
          "metadata": {
            "useLiteralContent": true
          }
        }
      },
      "imports": [
        "../utils/Context.sol"
      ],
      "versionPragmas": [
        "^0.8.0"
      ],
      "artifacts": [
        "Pausable"
      ]
    },
    "/Volumes/N/CoopHive/hive/hardhat/node_modules/.pnpm/@openzeppelin+contracts@4.9.5/node_modules/@openzeppelin/contracts/token/ERC20/extensions/ERC20Pausable.sol": {
      "lastModificationDate": 1706734039479,
      "contentHash": "b9e6238c7bb16f87e7562ad2857080df",
      "sourceName": "@openzeppelin/contracts/token/ERC20/extensions/ERC20Pausable.sol",
      "solcConfig": {
        "version": "0.8.21",
        "settings": {
          "evmVersion": "paris",
          "optimizer": {
            "enabled": false,
            "runs": 200
          },
          "outputSelection": {
            "*": {
              "*": [
                "abi",
                "evm.bytecode",
                "evm.deployedBytecode",
                "evm.methodIdentifiers",
                "metadata",
                "devdoc",
                "userdoc",
                "storageLayout",
                "evm.gasEstimates"
              ],
              "": [
                "ast"
              ]
            }
          },
          "metadata": {
            "useLiteralContent": true
          }
        }
      },
      "imports": [
        "../ERC20.sol",
        "../../../security/Pausable.sol"
      ],
      "versionPragmas": [
        "^0.8.0"
      ],
      "artifacts": [
        "ERC20Pausable"
      ]
    },
    "/Volumes/N/CoopHive/hive/hardhat/node_modules/.pnpm/@openzeppelin+contracts@4.9.5/node_modules/@openzeppelin/contracts/token/ERC20/ERC20.sol": {
      "lastModificationDate": 1706734039478,
      "contentHash": "3ae5166c6827a9cf1a7a462d1632b464",
      "sourceName": "@openzeppelin/contracts/token/ERC20/ERC20.sol",
      "solcConfig": {
        "version": "0.8.21",
        "settings": {
          "evmVersion": "paris",
          "optimizer": {
            "enabled": false,
            "runs": 200
          },
          "outputSelection": {
            "*": {
              "*": [
                "abi",
                "evm.bytecode",
                "evm.deployedBytecode",
                "evm.methodIdentifiers",
                "metadata",
                "devdoc",
                "userdoc",
                "storageLayout",
                "evm.gasEstimates"
              ],
              "": [
                "ast"
              ]
            }
          },
          "metadata": {
            "useLiteralContent": true
          }
        }
      },
      "imports": [
        "./IERC20.sol",
        "./extensions/IERC20Metadata.sol",
        "../../utils/Context.sol"
      ],
      "versionPragmas": [
        "^0.8.0"
      ],
      "artifacts": [
        "ERC20"
      ]
    },
    "/Volumes/N/CoopHive/hive/hardhat/node_modules/.pnpm/@openzeppelin+contracts@4.9.5/node_modules/@openzeppelin/contracts/token/ERC20/IERC20.sol": {
      "lastModificationDate": 1706734039496,
      "contentHash": "df36f7051335cd1e748b1b6463b7fdd3",
      "sourceName": "@openzeppelin/contracts/token/ERC20/IERC20.sol",
      "solcConfig": {
        "version": "0.8.21",
        "settings": {
          "evmVersion": "paris",
          "optimizer": {
            "enabled": false,
            "runs": 200
          },
          "outputSelection": {
            "*": {
              "*": [
                "abi",
                "evm.bytecode",
                "evm.deployedBytecode",
                "evm.methodIdentifiers",
                "metadata",
                "devdoc",
                "userdoc",
                "storageLayout",
                "evm.gasEstimates"
              ],
              "": [
                "ast"
              ]
            }
          },
          "metadata": {
            "useLiteralContent": true
          }
        }
      },
      "imports": [],
      "versionPragmas": [
        "^0.8.0"
      ],
      "artifacts": [
        "IERC20"
      ]
    },
    "/Volumes/N/CoopHive/hive/hardhat/node_modules/.pnpm/@openzeppelin+contracts@4.9.5/node_modules/@openzeppelin/contracts/token/ERC20/extensions/IERC20Metadata.sol": {
      "lastModificationDate": 1706734039497,
      "contentHash": "909ab67fc5c25033fe6cd364f8c056f9",
      "sourceName": "@openzeppelin/contracts/token/ERC20/extensions/IERC20Metadata.sol",
      "solcConfig": {
        "version": "0.8.21",
        "settings": {
          "evmVersion": "paris",
          "optimizer": {
            "enabled": false,
            "runs": 200
          },
          "outputSelection": {
            "*": {
              "*": [
                "abi",
                "evm.bytecode",
                "evm.deployedBytecode",
                "evm.methodIdentifiers",
                "metadata",
                "devdoc",
                "userdoc",
                "storageLayout",
                "evm.gasEstimates"
              ],
              "": [
                "ast"
              ]
            }
          },
          "metadata": {
            "useLiteralContent": true
          }
        }
      },
      "imports": [
        "../IERC20.sol"
      ],
      "versionPragmas": [
        "^0.8.0"
      ],
      "artifacts": [
        "IERC20Metadata"
      ]
    },
    "/Volumes/N/CoopHive/hive/hardhat/contracts/IHiveToken.sol": {
      "lastModificationDate": 1706568289169,
      "contentHash": "7f50e5cee56a6b2791416b5115d8d2da",
      "sourceName": "contracts/IHiveToken.sol",
      "solcConfig": {
        "version": "0.8.21",
        "settings": {
          "evmVersion": "paris",
          "optimizer": {
            "enabled": false,
            "runs": 200
          },
          "outputSelection": {
            "*": {
              "*": [
                "abi",
                "evm.bytecode",
                "evm.deployedBytecode",
                "evm.methodIdentifiers",
                "metadata",
                "devdoc",
                "userdoc",
                "storageLayout",
                "evm.gasEstimates"
              ],
              "": [
                "ast"
              ]
            }
          },
          "metadata": {
            "useLiteralContent": true
          }
        }
      },
      "imports": [
        "@openzeppelin/contracts/token/ERC20/IERC20.sol"
      ],
      "versionPragmas": [
        "^0.8.6"
      ],
      "artifacts": [
        "IHiveToken"
      ]
    },
    "/Volumes/N/CoopHive/hive/hardhat/contracts/HivePayments.sol": {
      "lastModificationDate": 1707051865133,
      "contentHash": "1e2333ea1139d93c1669ce4750c0e361",
      "sourceName": "contracts/HivePayments.sol",
      "solcConfig": {
        "version": "0.8.21",
        "settings": {
          "evmVersion": "paris",
          "optimizer": {
            "enabled": false,
            "runs": 200
          },
          "outputSelection": {
            "*": {
              "*": [
                "abi",
                "evm.bytecode",
                "evm.deployedBytecode",
                "evm.methodIdentifiers",
                "metadata",
                "devdoc",
                "userdoc",
                "storageLayout",
                "evm.gasEstimates"
              ],
              "": [
                "ast"
              ]
            }
          },
          "metadata": {
            "useLiteralContent": true
          }
        }
      },
      "imports": [
        "@openzeppelin/contracts-upgradeable/proxy/utils/Initializable.sol",
        "./IHiveToken.sol",
        "./ControllerOwnable.sol",
        "./IHivePayments.sol"
      ],
      "versionPragmas": [
        "^0.8.6"
      ],
      "artifacts": [
        "HivePayments"
      ]
    },
    "/Volumes/N/CoopHive/hive/hardhat/contracts/HivePaymentsTestable.sol": {
      "lastModificationDate": 1706568289166,
      "contentHash": "147994c0317c4b8f883662a418e8fc8c",
      "sourceName": "contracts/HivePaymentsTestable.sol",
      "solcConfig": {
        "version": "0.8.21",
        "settings": {
          "evmVersion": "paris",
          "optimizer": {
            "enabled": false,
            "runs": 200
          },
          "outputSelection": {
            "*": {
              "*": [
                "abi",
                "evm.bytecode",
                "evm.deployedBytecode",
                "evm.methodIdentifiers",
                "metadata",
                "devdoc",
                "userdoc",
                "storageLayout",
                "evm.gasEstimates"
              ],
              "": [
                "ast"
              ]
            }
          },
          "metadata": {
            "useLiteralContent": true
          }
        }
      },
      "imports": [
        "./HivePayments.sol"
      ],
      "versionPragmas": [
        "^0.8.6"
      ],
      "artifacts": [
        "HivePaymentsTestable"
      ]
    },
    "/Volumes/N/CoopHive/hive/hardhat/contracts/HiveOnChainJobCreator.sol": {
      "lastModificationDate": 1706568289166,
      "contentHash": "17b1a97e73d1c33e333d30af1047ef95",
      "sourceName": "contracts/HiveOnChainJobCreator.sol",
      "solcConfig": {
        "version": "0.8.21",
        "settings": {
          "evmVersion": "paris",
          "optimizer": {
            "enabled": false,
            "runs": 200
          },
          "outputSelection": {
            "*": {
              "*": [
                "abi",
                "evm.bytecode",
                "evm.deployedBytecode",
                "evm.methodIdentifiers",
                "metadata",
                "devdoc",
                "userdoc",
                "storageLayout",
                "evm.gasEstimates"
              ],
              "": [
                "ast"
              ]
            }
          },
          "metadata": {
            "useLiteralContent": true
          }
        }
      },
      "imports": [
        "@openzeppelin/contracts/access/Ownable.sol",
        "@openzeppelin/contracts-upgradeable/proxy/utils/Initializable.sol",
        "./SharedStructs.sol",
        "./IHiveJobManager.sol",
        "./IHiveJobClient.sol",
        "./ControllerOwnable.sol",
        "./IHiveToken.sol"
      ],
      "versionPragmas": [
        "^0.8.6"
      ],
      "artifacts": [
        "HiveOnChainJobCreator"
      ]
    },
    "/Volumes/N/CoopHive/hive/hardhat/contracts/IHiveJobManager.sol": {
      "lastModificationDate": 1706568289168,
      "contentHash": "557cb3bc5b5ff15cdcdba8419f22d0b9",
      "sourceName": "contracts/IHiveJobManager.sol",
      "solcConfig": {
        "version": "0.8.21",
        "settings": {
          "evmVersion": "paris",
          "optimizer": {
            "enabled": false,
            "runs": 200
          },
          "outputSelection": {
            "*": {
              "*": [
                "abi",
                "evm.bytecode",
                "evm.deployedBytecode",
                "evm.methodIdentifiers",
                "metadata",
                "devdoc",
                "userdoc",
                "storageLayout",
                "evm.gasEstimates"
              ],
              "": [
                "ast"
              ]
            }
          },
          "metadata": {
            "useLiteralContent": true
          }
        }
      },
      "imports": [
        "./IHiveJobClient.sol"
      ],
      "versionPragmas": [
        "^0.8.6"
      ],
      "artifacts": [
        "IHiveJobManager"
      ]
    },
    "/Volumes/N/CoopHive/hive/hardhat/contracts/IHiveJobClient.sol": {
      "lastModificationDate": 1706568289168,
      "contentHash": "5b8efe3db371b4d39b202766f91d097c",
      "sourceName": "contracts/IHiveJobClient.sol",
      "solcConfig": {
        "version": "0.8.21",
        "settings": {
          "evmVersion": "paris",
          "optimizer": {
            "enabled": false,
            "runs": 200
          },
          "outputSelection": {
            "*": {
              "*": [
                "abi",
                "evm.bytecode",
                "evm.deployedBytecode",
                "evm.methodIdentifiers",
                "metadata",
                "devdoc",
                "userdoc",
                "storageLayout",
                "evm.gasEstimates"
              ],
              "": [
                "ast"
              ]
            }
          },
          "metadata": {
            "useLiteralContent": true
          }
        }
      },
      "imports": [],
      "versionPragmas": [
        "^0.8.6"
      ],
      "artifacts": [
        "IHiveJobClient"
      ]
    },
    "/Volumes/N/CoopHive/hive/hardhat/contracts/ExampleClient.sol": {
      "lastModificationDate": 1706568289165,
      "contentHash": "14a1ba23189fd3e4f12aeac0f6d3728f",
      "sourceName": "contracts/ExampleClient.sol",
      "solcConfig": {
        "version": "0.8.21",
        "settings": {
          "evmVersion": "paris",
          "optimizer": {
            "enabled": false,
            "runs": 200
          },
          "outputSelection": {
            "*": {
              "*": [
                "abi",
                "evm.bytecode",
                "evm.deployedBytecode",
                "evm.methodIdentifiers",
                "metadata",
                "devdoc",
                "userdoc",
                "storageLayout",
                "evm.gasEstimates"
              ],
              "": [
                "ast"
              ]
            }
          },
          "metadata": {
            "useLiteralContent": true
          }
        }
      },
      "imports": [
        "@openzeppelin/contracts/access/Ownable.sol",
        "@openzeppelin/contracts-upgradeable/proxy/utils/Initializable.sol",
        "./IHiveJobManager.sol",
        "./IHiveJobClient.sol"
      ],
      "versionPragmas": [
        "^0.8.6"
      ],
      "artifacts": [
        "ExampleClient"
      ]
    },
    "/Volumes/N/CoopHive/hive/hardhat/contracts/IHiveUsers.sol": {
      "lastModificationDate": 1706568289170,
      "contentHash": "f646a25ca87a4a39b5aacab1407b6895",
      "sourceName": "contracts/IHiveUsers.sol",
      "solcConfig": {
        "version": "0.8.21",
        "settings": {
          "evmVersion": "paris",
          "optimizer": {
            "enabled": false,
            "runs": 200
          },
          "outputSelection": {
            "*": {
              "*": [
                "abi",
                "evm.bytecode",
                "evm.deployedBytecode",
                "evm.methodIdentifiers",
                "metadata",
                "devdoc",
                "userdoc",
                "storageLayout",
                "evm.gasEstimates"
              ],
              "": [
                "ast"
              ]
            }
          },
          "metadata": {
            "useLiteralContent": true
          }
        }
      },
      "imports": [
        "./SharedStructs.sol"
      ],
      "versionPragmas": [
        "^0.8.6"
      ],
      "artifacts": [
        "IHiveUsers"
      ]
    },
    "/Volumes/N/CoopHive/hive/hardhat/contracts/HiveToken.sol": {
      "lastModificationDate": 1706827187371,
      "contentHash": "dc48fe488f4e56f313094230d77b4fa1",
      "sourceName": "contracts/HiveToken.sol",
      "solcConfig": {
        "version": "0.8.21",
        "settings": {
          "evmVersion": "paris",
          "optimizer": {
            "enabled": false,
            "runs": 200
          },
          "outputSelection": {
            "*": {
              "*": [
                "abi",
                "evm.bytecode",
                "evm.deployedBytecode",
                "evm.methodIdentifiers",
                "metadata",
                "devdoc",
                "userdoc",
                "storageLayout",
                "evm.gasEstimates"
              ],
              "": [
                "ast"
              ]
            }
          },
          "metadata": {
            "useLiteralContent": true
          }
        }
      },
      "imports": [
        "@openzeppelin/contracts/access/Ownable.sol",
        "@openzeppelin/contracts/token/ERC20/ERC20.sol",
        "@openzeppelin/contracts/token/ERC20/extensions/ERC20Pausable.sol",
        "./ControllerOwnable.sol"
      ],
      "versionPragmas": [
        "^0.8.6"
      ],
      "artifacts": [
        "HiveToken"
      ]
    },
    "/Volumes/N/CoopHive/hive/hardhat/contracts/HiveTokenTestable.sol": {
      "lastModificationDate": 1706568289167,
      "contentHash": "174d4774459a6a90fc5a4932972ec2bc",
      "sourceName": "contracts/HiveTokenTestable.sol",
      "solcConfig": {
        "version": "0.8.21",
        "settings": {
          "evmVersion": "paris",
          "optimizer": {
            "enabled": false,
            "runs": 200
          },
          "outputSelection": {
            "*": {
              "*": [
                "abi",
                "evm.bytecode",
                "evm.deployedBytecode",
                "evm.methodIdentifiers",
                "metadata",
                "devdoc",
                "userdoc",
                "storageLayout",
                "evm.gasEstimates"
              ],
              "": [
                "ast"
              ]
            }
          },
          "metadata": {
            "useLiteralContent": true
          }
        }
      },
      "imports": [
        "./HiveToken.sol"
      ],
      "versionPragmas": [
        "^0.8.6"
      ],
      "artifacts": [
        "HiveTokenTestable"
      ]
    }
  }
}
